gallium/__init__.py
gallium/console.py
gallium/core.py
gallium/interface.py
gallium/starter.py
gallium/loader/__init__.py
gallium/loader/basic.py
gallium/loader/common.py
gallium/loader/imagination.py
gallium-0.1.8.data/scripts/g2
gallium-0.1.8.data/scripts/g3
gallium-0.1.8.data/scripts/gallium
gallium-0.1.8.dist-info/DESCRIPTION.rst
gallium-0.1.8.dist-info/METADATA
gallium-0.1.8.dist-info/RECORD
gallium-0.1.8.dist-info/WHEEL
gallium-0.1.8.dist-info/metadata.json
gallium-0.1.8.dist-info/top_level.txt
