Metadata-Version: 2.0
Name: gallium
Version: 0.1.8
Summary: A micro CLI development framework
Home-page: https://github.com/shiroyuki/carbon
Author: Juti Noppornpitak
Author-email: juti_n@yahoo.co.jp
License: MIT
Platform: UNKNOWN
Classifier: Development Status :: 5 - Production/Stable
Classifier: Intended Audience :: Developers
Classifier: License :: OSI Approved :: MIT License
Classifier: Operating System :: OS Independent
Classifier: Programming Language :: Python
Classifier: Programming Language :: Python :: 2.7
Classifier: Programming Language :: Python :: 3
Classifier: Topic :: Software Development :: Libraries
Requires-Dist: imagination
Requires-Dist: kotoba
